Problema_B/Mezcladora.v
/* 
 * Autor: Sergio Garino Vargas
 * Carné: B73157
 * Fecha de entrega: 9/12/2022
 */

module Mezcladora (
    input Clk, Reset,
    input IN, TOK, P1, P2,
    output V1, V2, V3, M, T, S, B);

/*
 * Defino dos vectores, uno de estado presente y otro para el próximo estado
 * los cuales son de tamaño tres por que el diseño de la ASM se tiene 5 
 * estados posibles que son requesentables con 3 bits.
 */
reg [2:0] EstPres, ProxEst;     

/*
 * Hago la asignación de estados
 */
parameter a = 3'b000;
parameter b = 3'b001;
parameter c = 3'b010;
parameter d = 3'b011;
parameter e = 3'b100;

/*
 * Memoria de estados
 */
always @(posedge Clk, posedge Reset) 
    if (Reset) EstPres <= a;
    else       EstPres <= ProxEst;

/*
* Lógica de cálculo de próximo estado
*/
always @(*)
    case (EstPres)
        a:  if (IN) ProxEst = b;
            else    ProxEst = a;

        b:  if (P1) ProxEst = c;
            else    ProxEst = b;

        c:  if (TOK) ProxEst = d;
            else     ProxEst = c;

        d:  if (TOK) ProxEst = e;
            else     ProxEst = d;

        e:  case ({P1, P2})
                2'b00: ProxEst = a; // P1= 0, P2 = 0
                2'b01: ProxEst = e; // P1= 0, P2 = 1
                2'b10: ProxEst = e; // P1= 1, P2 = 0
                2'b11: ProxEst = e; // P1= 1, P2 = 1
            endcase
    endcase   

/*
 * Lógica de cálculo de salidas
 */
assign V1 = (EstPres == b) ;
assign V2 = (EstPres == b) | (EstPres == c);
assign V3 = (EstPres == c & TOK & ~Clk) | (EstPres == d);
assign M = (EstPres == c) | (EstPres == d);
assign T = (EstPres == d);
assign T = ~(EstPres == c);
assign S = (EstPres == c) | (EstPres == d);
assign B = (EstPres == e & P1) | (EstPres == e & !P1 & P2);

endmodule

Problema_B/TB_Mezcladora.v
/* 
 * Autor: Sergio Garino Vargas
 * Carné: B73157
 * Fecha de entrega: 9/12/2022
 *
 */
`timescale 1ns/1ps

module Test_Mezcladora;

    reg Clk, Reset;
    reg IN, TOK, P1, P2;

    wire V1, V2, V3, M, T, S, B;

    reg [3:0] testvectors [12:0];
    integer vectornum;

    Mezcladora uut (
        .Clk(Clk) , .Reset(Reset) ,
        .IN(IN) , .TOK(TOK) , .P1(P1) , .P2(P2) ,
        .V1(V1) , .V2(V2) , .V3(V3) , .M(M) , .T(T) , .S(S) , .B(B)
        );

    initial 
        begin
            /* IN, TOK, P1, P2 */
            testvectors[0] = 4'b0000; // IN=0 TOK=x P1=x P2=x a
            testvectors[1] = 4'b1000; // IN=1 TOK=x P1=x P2=x pasa a b
            testvectors[2] = 4'b0000; // IN=x TOK=x P1=0 P2=x se queda en b
            testvectors[3] = 4'b0010; // IN=X TOK=X P1=1 P2=X PASA A C
            testvectors[4] = 4'b0011; // IN= TOK=0 P1= P2= SE QUEDA EN C
            testvectors[5] = 4'b0111; // IN= TOK=1 P1= P2= PASA A D
            testvectors[6] = 4'b0011; // IN= TOK=0 P1= P2= SE QUEDA EN D
            testvectors[7] = 4'b0111; // IN= TOK=1 P1= P2= PASA A E
            testvectors[8] = 4'b0010; // IN= TOK= P1=1 P2= SE QUEDA EN E 
            testvectors[9] = 4'b0001; // IN= TOK= P1=0 P2=1 SE QUEDA EN E
            testvectors[10] = 4'b0000; // IN= TOK= P1=0 P2=0 VA A a
            testvectors[11] = 4'b0000;
            testvectors[12] = 4'b0000;
            //testvectors[x] = 4'bXXXX; // IN= TOK= P1= P2=

            vectornum = 0;

            Reset = 1;
            #3 Reset = 0;

            $dumpfile("Mezcla.vcd");
            $dumpvars(0, Test_Mezcladora);

        end 

    always 
        begin
            Clk = 1; #5; Clk = 0; #5;
        end

    always @ (negedge Clk) 
        begin
            {IN, TOK, P1, P2} = testvectors [vectornum];
            $display;
                $display ("Las entradas son IN = %b, TOK = %b, P1 = %b, P2 = %b", IN, TOK, P1, P2);
        end

    always @ (posedge Clk) 
    #1 if (!Reset)
        begin
            $display ("Las salidas son V1=%b, V2=%b, V3=%b, M=%b, T=%b, S=%b, B=%b", V1, V2, V3, M, T, S, B);
            vectornum = vectornum + 1;
                if (vectornum == 13)
                    $finish;
        end

endmodule

Problema_B/Mezcla.vcd
$date
	Thu Dec  8 23:45:25 2022
$end
$version
	Icarus Verilog
$end
$timescale
	1ps
$end
$scope module Test_Mezcladora $end
$var wire 1 ! T $end
$var wire 1 " V3 $end
$var wire 1 # V2 $end
$var wire 1 $ V1 $end
$var wire 1 % S $end
$var wire 1 & M $end
$var wire 1 ' B $end
$var reg 1 ( Clk $end
$var reg 1 ) IN $end
$var reg 1 * P1 $end
$var reg 1 + P2 $end
$var reg 1 , Reset $end
$var reg 1 - TOK $end
$var integer 32 . vectornum [31:0] $end
$scope module uut $end
$var wire 1 ' B $end
$var wire 1 ( Clk $end
$var wire 1 ) IN $end
$var wire 1 & M $end
$var wire 1 * P1 $end
$var wire 1 + P2 $end
$var wire 1 , Reset $end
$var wire 1 % S $end
$var wire 1 ! T $end
$var wire 1 - TOK $end
$var wire 1 # V2 $end
$var wire 1 " V3 $end
$var wire 1 $ V1 $end
$var reg 3 / EstPres [2:0] $end
$var reg 3 0 ProxEst [2:0] $end
$upscope $end
$upscope $end
$enddefinitions $end
#3000
$dumpvars
b0 0
b0 /
b0 .
x-
0,
x+
x*
x)
1(
0'
0&
0%
0$
0#
0"
x!
$end
#5000
0)
0-
0*
0+
0(
#10000
1(
#11000
b1 .
#15000
b1 0
1)
0(
#20000
1#
1$
b1 /
1(
#21000
b10 .
#25000
0)
0(
#30000
1(
#31000
b11 .
#35000
b10 0
1*
0(
#40000
1&
0!
1%
0$
b10 /
1(
#41000
b100 .
#45000
1+
0(
#50000
1(
#51000
b101 .
#55000
1"
b11 0
1-
0(
#60000
b100 0
0#
1!
b11 /
1"
1(
#61000
b110 .
#65000
b11 0
0-
0(
#70000
1(
#71000
b111 .
#75000
b100 0
1-
0(
#80000
1'
0"
0&
0%
x!
b100 /
1(
#81000
b1000 .
#85000
0-
0+
0(
#90000
1(
#91000
b1001 .
#95000
0*
1+
0(
#100000
1(
#101000
b1010 .
#105000
0'
b0 0
0+
0(
#110000
b0 /
1(
#111000
b1011 .
#115000
0(
#120000
1(
#121000
b1100 .
#125000
0(
#130000
1(
#131000
b1101 .
